[
    {
        "name" : "vicelio",
        "color" : "#cf3e3e",
        "rank" : 12,
        "kills" : 145,
        "deaths" : 87
    },
    {
        "name" : "RackJonan",
        "color" : "#2f703d",
        "rank" : 30,
        "kills" : 1754,
        "deaths" : 501
    },
    {
        "name" : "rexadde",
        "color" : "#41aaa9",
        "rank" : 16,
        "kills" : 200,
        "deaths" : 226
    },
    {
        "name" : "StephanSwinford",
        "color" : "#ffdb41",
        "rank" : 4,
        "kills" : 32,
        "deaths" : 60
    },
    {
        "name" : "Swarmmm",
        "color" : "#cf3e3e",
        "rank" : 3,
        "kills" : 25,
        "deaths" : 7
    },
    {
        "name" : "no1dead",
        "color" : "#d4d4d4",
        "rank" : 45,
        "kills" : 3456,
        "deaths" : 2965
    },
    {
        "name" : "AssaultCommand",
        "color" : "#fb8b9f",
        "rank" : 10,
        "kills" : 122,
        "deaths" : 120
    },
    {
        "name" : "devDorito",
        "color" : "#e97339",
        "rank" : 41,
        "kills" : 2763,
        "deaths" : 3054
    },
    {
        "name" : "DEElekgolo",
        "color" : "#2f703d",
        "rank" : 34,
        "kills" : 1798,
        "deaths" : 1504
    },
    {
        "name" : "emoose",
        "color" : "#ffdb41",
        "rank" : 49,
        "kills" : 6942,
        "deaths" : 4780
    },
    {
        "name" : "Wunk",
        "color" : "#2f703d",
        "rank" : 47,
        "kills" : 5875,
        "deaths" : 6700
    },
    {
        "name" : "Shockfire",
        "color" : "#375799",
        "rank" : 37,
        "kills" : 2001,
        "deaths" : 911
    },
    {
        "name" : "ihatecompvir",
        "color" : "#41aaa9",
        "rank" : 42,
        "kills" : 4200,
        "deaths" : 2432
    },
    {
        "name" : "Gamecheat13",
        "color" : "#375799",
        "rank" : 30,
        "kills" : 2699,
        "deaths" : 3075
    },
    {
        "name" : "Woovie",
        "color" : "#cf3e3e",
        "rank" : 39,
        "kills" : 3661,
        "deaths" : 1954
    },
    {
        "name" : "Pyong",
        "color" : "#d4d4d4",
        "rank" : 3,
        "kills" : 27,
        "deaths" : 56
    },
    {
        "name" : "pwnsrv",
        "color" : "#41aaa9",
        "rank" : 8,
        "kills" : 101,
        "deaths" : 87
    },
    {
        "name" : "Chaosvex",
        "color" : "#fb8b9f",
        "rank" : 37,
        "kills" : 3000,
        "deaths" : 3256
    },
    {
        "name" : "Fishphd",
        "color" : "#cf3e3e",
        "rank" : 1,
        "kills" : 12,
        "deaths" : 4
    },
    {
        "name" : "Bivi",
        "color" : "#5a5a5a",
        "rank" : 7,
        "kills" : 89,
        "deaths" : 87
    },
    {
        "name" : "Insane",
        "color" : "#375799",
        "rank" : 46,
        "kills" : 3904,
        "deaths" : 2578
    },
    {
        "name" : "Sn_420",
        "color" : "#2f703d",
        "rank" : 19,
        "kills" : 1508,
        "deaths" : 1785
    },
    {
        "name" : "Woolba",
        "color" : "#e97339",
        "rank" : 14,
        "kills" : 985,
        "deaths" : 643
    },
    {
        "name" : "noob622",
        "color" : "#ffdb41",
        "rank" : 26,
        "kills" : 1867,
        "deaths" : 2498
    }
]
